env_banner-0.1.0.dist-info/licenses/LICENSE
envbanner/__init__.py
envbanner/adapters.py
envbanner/core.py
envbanner/middleware.py
envbanner/streamlit_adapter.py
env_banner-0.1.0.dist-info/METADATA
env_banner-0.1.0.dist-info/WHEEL
env_banner-0.1.0.dist-info/top_level.txt
env_banner-0.1.0.dist-info/RECORD
