Metadata-Version: 2.4
Name: env-banner
Version: 0.1.0
Summary: A universal environment banner for Python web frameworks.
License: MIT License
Project-URL: Homepage, https://github.com/sagearbor/env-banner-python
Project-URL: Repository, https://github.com/sagearbor/env-banner-python
Project-URL: Issues, https://github.com/sagearbor/env-banner-python/issues
Classifier: Programming Language :: Python :: 3
Classifier: License :: OSI Approved :: MIT License
Classifier: Operating System :: OS Independent
Classifier: Framework :: FastAPI
Classifier: Framework :: Flask
Classifier: Framework :: Django
Requires-Python: >=3.8
License-File: LICENSE
Dynamic: license-file
